caesar_cipher_test
