Metadata-Version: 2.1
Name: caesar-cipher-test
Version: 0.0.5
Summary: A caesar cipher app and simple python calculator
Home-page: UNKNOWN
Author: Berhanu Dagnew
Author-email: babipanda.learn@gmail.com
License: MIT
Platform: UNKNOWN
Classifier: Development Status :: 5 - Production/Stable
Classifier: Intended Audience :: Education
Classifier: Operating System :: POSIX :: Linux
Classifier: License :: OSI Approved :: MIT License
Classifier: Programming Language :: Python :: 3
